{
  "meta_title": "Farmácia e Drogaria na Vila Zelina com o menor preço - Drogazelina",
  "meta_description": "Está procurando uma Farmácia e Drogaria na Vila Zelina com o menor preço e o melhor que entrega em sua casa, acesse nosso site e faça já seu pedido!",
  "sections": [
    {
      "type": "banner-slider",
      "autoplay": 9000,
      "slides": [
        {
          "start": "2022-04-29T15:34:45.543Z",
          "end": "2022-06-30T17:18:31.447Z",
          "img": "/img/uploads/apresente-este-codigo-drogazelina-no-balcao-de-nossas-duas-unidades-e-ganhe-um-desconto-de-r-10-00-no-teste.png",
          "mobile_img": "/img/uploads/banner-responsivo-zelina-2-.png",
          "link": "https://drogazelina.com.br/search?term=culturelle",
          "alt": "Culturelle"
        },
        {
          "start": "2021-12-28T20:08:58.851Z",
          "end": "2022-06-30T20:08:58.887Z",
          "img": "/img/uploads/testecovid-vila-zelina.png",
          "mobile_img": "/img/uploads/banner-responsivo-zelina-1-.png",
          "link": "https://api.whatsapp.com/send/?phone=5511963942419&text&app_absent=0",
          "alt": "Teste Covid-19 Vila Zelina"
        },
        {
          "start": "2021-11-01T16:21:29.350Z",
          "end": "2022-06-30T16:19:21.178Z",
          "img": "/img/uploads/banner.png",
          "mobile_img": "/img/uploads/banner-480-px-300-px-.png",
          "link": "https://drogazelina.com.br/search?term=vichy",
          "alt": "Produtos Vichy"
        },
        {
          "start": "2021-07-23T19:33:03.749Z",
          "end": "",
          "img": "/img/uploads/a_sua_drogaria.png",
          "mobile_img": "/img/uploads/copia_de_a_sua_drogaria.png"
        }
      ],
      "full_width": false
    },
    {
      "type": "info-bar",
      "enabled": true
    },
    {
      "type": "collection-shelf",
      "shuffle": true,
      "collection_id": "61169e84cfbcd970597d22ff:categories:Ofertas:/saude-e-bem-estar",
      "limit": 24,
      "page": 1,
      "sort": "sales",
      "title": "Confira nossas Ofertas!"
    },
    {
      "type": "collection-shelf",
      "shuffle": true,
      "limit": 24,
      "page": 1,
      "sort": "news"
    },
    {
      "type": "collection-shelf",
      "shuffle": false,
      "limit": 24,
      "page": 1,
      "collection_id": "6123f8cccfbcd9705986f64e:categories:Tratamento Capilar:/tratamento-capilar",
      "sort": "views",
      "headless": false,
      "title": "Produtos Incríveis para cuidar de você!"
    },
    {
      "type": "page-title",
      "title": "Farmácia e Drogaria com o menor preço - Drogazelina",
      "description": "Está procurando uma Farmácia e Drogaria com o menor preço e o melhor que entrega em sua casa, acesse nosso site e faça já seu pedido!"
    },
    {
      "type": "custom-html",
      "html": "<div class=\"row\" style=\"margin-left: -10px; margin-right: -10px;\">\n<div class=\"col-md-4\" style=\"padding: 10px;\"><a class=\"image-link\" href=\"https://marketingmr1.netlify.app/kit-renu-fresh-para-lentes-solucao-com-355ml--solucao-com-120ml--estojo-para-lentes\" title=\"renufresh\"> <img alt=\"renufresh\" height=\"269\" src=\"/img/uploads/renufresh.jpg\" title=\"renufresh\" width=\"367\" /> </a></div>\n<div class=\"col-md-4\" style=\"padding: 10px;\"><a class=\"image-link\" href=\"https://marketingmr1.netlify.app/dermocosmeticos\" title=\"dermocosméticos\"> <img alt=\"dermocosméticos\" height=\"269\" src=\"/img/uploads/loja-de-dermocosmeticos.jpg\" title=\"dermocosméticos\" width=\"367\" /> </a></div>\n<div class=\"col-md-4\" style=\"padding: 10px;\"><a class=\"image-link\" href=\"https://marketingmr1.netlify.app/pages/entrega\" title=\"Farmácia com entrega\"> <img alt=\"Farmácia com entrega\" height=\"269\" src=\"/img/uploads/farmacia-com-delivery.jpg\" title=\"Farmácia com entrega\" width=\"367\" /> </a></div>\n</div>"
    }
  ]
}